yaz_pynotify/__init__.py
yaz_pynotify/py.typed
yaz_pynotify/settings.py
yaz_pynotify/messaging_service/__init__.py
yaz_pynotify/messaging_service/factory.py
yaz_pynotify/messaging_service/types.py
yaz_pynotify/messaging_service/services/__init__.py
yaz_pynotify/messaging_service/services/base.py
yaz_pynotify/messaging_service/services/email.py
yaz_pynotify/messaging_service/services/sms.py
yaz_pynotify/notification_service/__init__.py
yaz_pynotify/notification_service/client.py
yaz_pynotify/notification_service/config.py
yaz_pynotify/notification_service/handlers/__init__.py
yaz_pynotify/notification_service/handlers/base.py
yaz_pynotify/notification_service/handlers/email.py
yaz_pynotify/notification_service/handlers/sms.py
yaz_pynotify-0.0.1.dist-info/METADATA
yaz_pynotify-0.0.1.dist-info/WHEEL
yaz_pynotify-0.0.1.dist-info/licenses/LICENSE
yaz_pynotify-0.0.1.dist-info/RECORD
