Metadata-Version: 2.3
Name: yaz_pynotify
Version: 0.0.1
Summary: PyNotify is a flexible and extendable notification system that supports multiple notification channels like email and SMS.
Project-URL: Homepage, https://github.com/yarz-dev/pynotify_client
Project-URL: Issues, https://github.com/yarz-dev/pynotify_client/issues
Author-email: Yarzue Zolia <zyarzue.dev@gmail.com>
License-File: LICENSE
Classifier: License :: OSI Approved :: MIT License
Classifier: Operating System :: OS Independent
Classifier: Programming Language :: Python :: 3
Requires-Python: >=3.10
